setup.py
ipycomms/__init__.py
ipycomms.egg-info/PKG-INFO
ipycomms.egg-info/SOURCES.txt
ipycomms.egg-info/dependency_links.txt
ipycomms.egg-info/not-zip-safe
ipycomms.egg-info/top_level.txt