Metadata-Version: 1.0
Name: ipycomms
Version: 0.1
Summary: Lightweight messaging between IPython / Jupyter notebooks and Javascript
Home-page: https://github.com/sbirch/ipycomms/tree/master
Author: Sam Birch
Author-email: sam.m.birch@gmail.com
License: MIT
Platform: UNKNOWN
